rrshare/RQSetting/__init__.py
rrshare/RQSetting/cache.py
rrshare/RQSetting/executor.py
rrshare/RQSetting/rqLocalize.py
rrshare/Timer.py
rrshare/__init__.py
rrshare/__main__.py
rrshare/cmds.py
rrshare/record_all_data.py
rrshare/record_all_data.sh
rrshare/rqFactor/__init__.py
rrshare/rqFactor/fetch_forecast_em.py
rrshare/rqFactor/stock_RS_OH_MA.py
rrshare/rqFactor/swl_RS_OH_MA.py
rrshare/rqFactor/swl_rs_valuation_pg_L123.py
rrshare/rqFetch/\
rrshare/rqFetch/__init__.py
rrshare/rqFetch/base.py
rrshare/rqFetch/fetch_basic_tusharepro.py
rrshare/rqFetch/fetch_stock_day_adj_fillna_from_tusharepro.py
rrshare/rqFetch/fetch_stock_day_adj_fillna_tspro.py
rrshare/rqFetch/fetch_stock_day_fq_from_tusharepro.py
rrshare/rqFetch/fetch_sw_index_class_L1_L2_from_swsindex.py
rrshare/rqFetch/fetch_sw_index_daily.py
rrshare/rqFetch/fetch_swl_index_daily_and_realtime.py
rrshare/rqFetch/fetch_swsindex_daily.py
rrshare/rqFetch/rqCodeName.py
rrshare/rqFetch/rqFetchSnapshot_eq.py
rrshare/rqFetch/rqTusharepro.py
rrshare/rqSU/__init__.py
rrshare/rqSU/save_daily_counts_to_pikle.py
rrshare/rqSU/save_swl_daily_valucation.py
rrshare/rqSU/save_swl_list.py
rrshare/rqSU/save_tusharepro_pg.py
rrshare/rqUpdate/__init__.py
rrshare/rqUpdate/update_daily_counts_pickle.py
rrshare/rqUpdate/update_stock_RS_OH_MA.py
rrshare/rqUpdate/update_stock_day.py
rrshare/rqUpdate/update_stock_realtime_PRS.py
rrshare/rqUpdate/update_swl1_index_realtime.py
rrshare/rqUpdate/update_swl_RS_OH_MA.py
rrshare/rqUpdate/update_swl_day.py
rrshare/rqUpdate/update_swl_rs_valuation.py
rrshare/rqUtil/__init__.py
rrshare/rqUtil/client_postgsql.py
rrshare/rqUtil/config_postgresql.py
rrshare/rqUtil/config_setting.py
rrshare/rqUtil/rqCache.py
rrshare/rqUtil/rqCode.py
rrshare/rqUtil/rqCsv.py
rrshare/rqUtil/rqDate.py
rrshare/rqUtil/rqDate_trade.py
rrshare/rqUtil/rqDecorator.py
rrshare/rqUtil/rqLocalize.py
rrshare/rqUtil/rqLogs.py
rrshare/rqUtil/rqParameter.py
rrshare/rqUtil/rqPgsql.py
rrshare/rqUtil/rqSetting.py
rrshare-4.2.8.dist-info/entry_points.txt
rrshare-4.2.8.dist-info/WHEEL
rrshare-4.2.8.dist-info/METADATA
rrshare-4.2.8.dist-info/RECORD
