Metadata-Version: 2.1
Name: rrshare
Version: 4.2.8
Summary: stock data(from tusharepro) & analysis
License: MIT
Author: rome
Requires-Python: >=3.10,<4.0
Classifier: License :: OSI Approved :: MIT License
Classifier: Programming Language :: Python :: 3
Classifier: Programming Language :: Python :: 3.10
Requires-Dist: click (>=8.1.0,<9.0.0)
Requires-Dist: easyquotation (>=0.7.5,<0.8.0)
Requires-Dist: tushare (>=1.2.62,<2.0.0)
Requires-Dist: zenlog (>=1.1,<2.0)
